enverge_open_from_badge/__init__.py
enverge_open_from_badge/_version.py
enverge_open_from_badge/service/__init__.py
enverge_open_from_badge/service/open_repo_service.py
jupyterhub_enverge_open_from_badge-0.0.2.dist-info/LICENSE
jupyterhub_enverge_open_from_badge-0.0.2.dist-info/METADATA
jupyterhub_enverge_open_from_badge-0.0.2.dist-info/WHEEL
jupyterhub_enverge_open_from_badge-0.0.2.dist-info/top_level.txt
jupyterhub_enverge_open_from_badge-0.0.2.dist-info/RECORD
