Metadata-Version: 2.2
Name: jupyterhub-enverge-open-from-badge
Version: 0.0.2
Summary: JupyterHub Enverge Open From Badge
Home-page: https://github.com/Enverge-Labs/enverge_open_from_badge
Author: Tudor M
Author-email: tudor@enverge.ai
License: 3 Clause BSD
Requires-Python: >=3.10
License-File: LICENSE
Requires-Dist: jupyterhub>=4.1.6
Dynamic: author
Dynamic: author-email
Dynamic: description
Dynamic: description-content-type
Dynamic: home-page
Dynamic: license
Dynamic: requires-dist
Dynamic: requires-python
Dynamic: summary
